masonite/validation/MessageBag.py
masonite/validation/RuleEnclosure.py
masonite/validation/Validator.py
masonite/validation/__init__.py
masonite/validation/decorators.py
masonite/validation/commands/RuleCommand.py
masonite/validation/commands/RuleEnclosureCommand.py
masonite/validation/commands/__init__.py
masonite/validation/providers/ValidationProvider.py
masonite/validation/providers/__init__.py
masonite/validation/snippets/scaffold/rule.html
masonite/validation/snippets/scaffold/rule_enclosure.html
masonite_validation-3.0.14.dist-info/METADATA
masonite_validation-3.0.14.dist-info/WHEEL
masonite_validation-3.0.14.dist-info/top_level.txt
masonite_validation-3.0.14.dist-info/RECORD
